sparrowDB/__init__.py
sparrowDB/config.py
sparrowDB/sparrow.py
sparrowDB/sparrow_clint.py
sparrowDB/sparrow_clint_service.py
sparrowDB/tools/__init__.py
sparrowDB/tools/error.py
sparrowDB-0.1.1.dist-info/METADATA
sparrowDB-0.1.1.dist-info/WHEEL
sparrowDB-0.1.1.dist-info/top_level.txt
sparrowDB-0.1.1.dist-info/RECORD
